__init__.py
tricahue.py
tricahue-0.0b6.dist-info/METADATA
tricahue-0.0b6.dist-info/WHEEL
tricahue-0.0b6.dist-info/top_level.txt
tricahue-0.0b6.dist-info/RECORD
