Metadata-Version: 2.4
Name: tricahue
Version: 0.0b6
Summary: This package extracts experimental data and metadata, converts to stardard formats, uploads to SynBioHub and Flapjack, and connects them
Author-email: Gonzalo Vidal <gonzalo.vidalpena@colorado.edu>
Maintainer-email: Gonzalo Vidal <gonzalo.vidalpena@colorado.edu>
License-Expression: MIT
Project-URL: Homepage, https://github.com/MyersResearchGroup/Tricahue
Project-URL: Bug Tracker, https://github.com/MyersResearchGroup/Tricahue/issues
Keywords: SBOL,test,data,experimental,synthetic biology
Classifier: Programming Language :: Python :: 3
Classifier: Operating System :: OS Independent
Requires-Python: >=3.7
Requires-Dist: excel2flapjack>=1.0.11
Requires-Dist: excel2sbol>=1.1.14
Requires-Dist: numpy==1.26.1
Requires-Dist: pandas==1.3.3
Provides-Extra: test
Requires-Dist: pytest<5.0.0; extra == "test"
Requires-Dist: pytest-cov[all]; extra == "test"
